{"cameraMode":{"drawMode":0,"name":"Shaded","section":"Shading Mode"},"sceneLighting":false,"audioPlay":false,"sceneViewState":{"m_AlwaysRefresh":false,"showFog":true,"showSkybox":false,"showFlares":true,"showImageEffects":true,"showParticleSystems":true,"showVisualEffectGraphs":true,"m_FxEnabled":true},"in2DMode":false,"pivot":{"x":0.16897940635681153,"y":-0.4263540506362915,"z":-0.56999671459198},"rotation":{"x":-0.4373258054256439,"y":-0.30978474020957949,"z":0.1620492786169052,"w":-0.8294537663459778},"size":1.9094913005828858,"orthographic":false}